src/bitorder_out.sv
`default_nettype none
`timescale 1ns / 1ps


module bitorder_out (
                input wire clk,
                input wire rst,
                input wire axiiv,
                input wire [7:0] axiid,

                output logic axiov,
                output logic [1:0] axiod 
                );

    //recieved in one clock cycles - [7:6],[5:4],[3:2],[1:0]
    //output in four clock cycle - 1:0 -> 3:2 -> 5:4 -> 7:6

    logic [1:0] counter_in;

    logic downtime;
    logic flipping;

    always_ff @(posedge clk) begin
        if (rst) begin
            downtime <= 1'b1;
            flipping <= 0;
        end else begin
            if(downtime) begin
                if(axiiv) begin
                    flipping <= 1'b1;
                    downtime <= 0;
                    counter_in <= 1'b1;
                    axiov <= 1'b1;
                    axiod <= axiid[1:0];
                end else begin
                    counter_in <= 0;
                    axiov <= 0;
                end
            end else if (flipping) begin
                if (axiiv) begin
                    counter_in <= (counter_in == 2'b11)? 0:counter_in +1'b1;
                    axiov <= 1'b1;
                    axiod <= axiid[(counter_in*2)+:2];
                end else begin
                    downtime <= 1'b1;
                    flipping <= 0;
                    axiov <= 0;
                end
            end
        end
    end
endmodule

`default_nettype wire

sim/bitorder_out_tb.sv
`default_nettype none
`timescale 1ns / 1ps

module bitorder_out_tb;
    logic clk;
    logic rst;

    logic axiiv;
    logic [7:0] axiid;
    logic axiov_out;
    logic [1:0] axiod_out;


    bitorder_out uut(
        .clk(clk),
        .rst(rst),
        .axiiv(axiiv),
        .axiid(axiid),
        .axiov(axiov_out),
        .axiod(axiod_out));

    
    always begin
        #10;
        clk = !clk;         //Now #20 will wait a clock period
    end

    initial begin
        $dumpfile("bitorder_out.vcd");
        $dumpvars(0, bitorder_out_tb);
        $display("Starting Sim");
        clk = 0;
        rst = 0;
        #30;
        rst = 1;
        #20;
        rst = 0;
        //READ IN FIRST BYTE
        axiid = 8'b1111_0011;
        axiiv = 1'b1;
        #20;
        axiid = 8'b1111_0011;
        axiiv = 1'b1;
        #20;        
        axiid = 8'b1111_0011;
        axiiv = 1'b1;
        #20;        
        axiid = 8'b1111_0011;
        axiiv = 1'b1;
        #20;
        //READ IN SECOND BYTE
        axiiv = 1'b1;
        axiid = 8'b0010_0110;
        #20;
        axiiv = 1'b1;
        axiid = 8'b0010_0110;
        #20;
        axiiv = 1'b1;
        axiid = 8'b0010_0110;
        #20;
        axiiv = 1'b1;
        axiid = 8'b0010_0110;
        #20;
        // //READ IN THIRD BYTE (WITH A STALL...)
        // axiiv = 1'b1;
        // axiid = 2'b00;
        // #20;
        // axiiv = 1'b1;
        // axiid = 2'b00;
        // #20;
        // axiiv = 1'b0;
        // axiid = 2'b11;
        // #20;
        // axiiv = 1'b1;
        // axiid = 2'b00;
        // #20; 
        // axiiv = 1'b1;
        // axiid = 2'b00;
        // #20;      
        // //READ IN FOURTH BYTE  
        // axiiv = 1'b1;
        // axiid = 2'b01;
        // #20;
        // axiiv = 1'b1;
        // axiid = 2'b01;
        // #20;
        // axiiv = 1'b1;
        // axiid = 2'b01;
        // #20;
        // axiiv = 1'b1;
        // axiid = 2'b11;
        // #20;      


    $display("Finishing Sim");
    $finish;
    end

endmodule

`default_nettype wire

bitorder_out.vcd
$date
	Wed Dec 14 09:48:40 2022
$end
$version
	Icarus Verilog
$end
$timescale
	1ps
$end
$scope module bitorder_out_tb $end
$var wire 1 ! axiov_out $end
$var wire 2 " axiod_out [1:0] $end
$var reg 8 # axiid [7:0] $end
$var reg 1 $ axiiv $end
$var reg 1 % clk $end
$var reg 1 & rst $end
$scope module uut $end
$var wire 8 ' axiid [7:0] $end
$var wire 1 $ axiiv $end
$var wire 1 % clk $end
$var wire 1 & rst $end
$var reg 2 ( axiod [1:0] $end
$var reg 1 ! axiov $end
$var reg 2 ) counter_in [1:0] $end
$var reg 1 * downtime $end
$var reg 1 + flipping $end
$upscope $end
$upscope $end
$enddefinitions $end
#0
$dumpvars
x+
x*
bx )
bx (
bx '
0&
0%
x$
bx #
bx "
x!
$end
#10000
1%
#20000
0%
#30000
0+
1*
1%
1&
#40000
0%
#50000
b11 "
b11 (
1!
b1 )
0*
1+
1%
1$
b11110011 #
b11110011 '
0&
#60000
0%
#70000
b0 "
b0 (
b10 )
1%
#80000
0%
#90000
b11 "
b11 (
b11 )
1%
#100000
0%
#110000
b0 )
1%
#120000
0%
#130000
b10 "
b10 (
b1 )
1%
b100110 #
b100110 '
#140000
0%
#150000
b1 "
b1 (
b10 )
1%
#160000
0%
#170000
b10 "
b10 (
b11 )
1%
#180000
0%
#190000
b0 "
b0 (
b0 )
1%
#200000
0%
#210000
b10 "
b10 (
b1 )
1%
