src/dummy_alg.sv
`timescale 1ns / 1ps
`default_nettype none

module dummy_alg (
	input wire clk_in,
	input wire rst_in,
	input wire complete,
	input wire [31:0][7:0] matA_row,
        input wire [31:0][7:0] matB_col,
	input wire [4:0] row_in,
	input wire [4:0] col_in, 
	input wire val_rows,

	output logic [4:0] row_req,
	output logic [4:0] col_req,
	output logic new_request,

	output logic [4:0] row_out,
	output logic [4:0] col_out,
	output logic [7:0] matrix_val,
	output logic valid_out,
	output logic done
	);


	logic complete_old;

	logic [1:0] control_state;

	always_ff @(posedge clk_in) begin
	  complete_old <= complete;
	  if(rst_in) begin
	    row_out <= 0;
	    col_out <= 0;
	    row_req <= 0;
	    col_req <= 0;
	    done <= 0;
	    matrix_val <= 0;
	    valid_out <= 0;
	    control_state <= 0;
	  end else begin
	    if(control_state==0 && !complete_old && complete) begin
	      control_state <= 1;
	      row_req <=0;
	      col_req <= 0;
	      new_request <= 1;
	      valid_out <= 0;
	    end else if (control_state==1) begin
	      if(val_rows) begin
		row_out <=  row_in;
		col_out <= col_in;
		matrix_val <= matA_row[col_in];
		valid_out <= 1;
		if(col_in >= 31) begin
		  if(row_in >= 31) begin
		    done <= 1;
		    control_state <= 0;
		  end else begin
		    row_req <= row_in + 1;
		    col_req <= 0;
		    new_request <= 1;
		  end
		end else begin
		  row_req <= row_in;
		  col_req <= col_in+1;
		  new_request <= 1;
		end
	      end
	    end
	  end
	end
	   	


endmodule

`default_nettype wire

sim/tb_iter_control.sv
`default_nettype none
`timescale 1ns / 1ps

module tb_iter_control;
  logic clk;
  logic rst;

  logic [31:0][7:0] row1;
  logic [31:0][7:0] col2;
  logic val_rows;

  logic val_out;
  logic [7:0] mat_out;
  
  logic complete;
  logic [4:0] row_in;
  logic [4:0] col_in;
  logic [4:0] row_req;
  logic [4:0] col_req;
  logic [4:0] row_out;
  logic [4:0] col_out;
 
  logic new_request;
  logic done;

  //iter_control test_iter_control(.clk_in(clk), .rst_in(rst), .matA_row(row1), .matB_col(col2), .val_rows(val_rows),
  //				 .row_in(row_in), .col_in(col_in), .row_req(row_req), .col_req(col_req), .new_request(new_request), 
  //				 .row_out(row_out), .col_out(col_out), .matrix_val(mat_out),
  //			         .complete(complete), .done(done), .valid_out(val_out));
  
  dummy_alg test_alg(.clk_in(clk), .rst_in(rst), .matA_row(row1), .matB_col(col2), .val_rows(val_rows),
                               .row_in(row_in), .col_in(col_in), .row_req(row_req), .col_req(col_req), .new_request(new_request),
                               .row_out(row_out), .col_out(col_out), .matrix_val(mat_out),
                               .complete(complete), .done(done), .valid_out(val_out));
  
  logic [31:0][31:0] mat1 [7:0];
  logic [31:0][31:0] mat2 [7:0];

  always begin
    #10;
    clk = !clk;
  end

  initial begin
        $dumpfile("iter_dummy.vcd"); //file to store value change dump (vcd)
        $dumpvars(0,tb_iter_control); //store everything at the current level and below
        $display("Starting Sim"); //print nice message
        clk = 0; //initialize clk (super important)
        rst = 0; //initialize rst (super important)
        complete = 0;
	mat1[0] = {8'h1, 8'h1, 8'h1};
	mat1[1] = {8'h2, 8'h2, 8'h2};
	mat1[2] = {8'h3, 8'h3, 8'h3};
                                      
        mat2[0] = {8'h1, 8'h0, 8'h0};
        mat2[1] = {8'h0, 8'h1, 8'h0};
        mat2[2] = {8'h0, 8'h0, 8'h1}; 

        #30  //wait a little bit of time at beginning
        rst = 1; //reset system
        #20; //hold high for a few clock cycles
        rst = 0;
        #20;

	complete = 1;
	#20;
	complete = 0;
	#60

	while(~done) begin
	  if(new_request) begin
	    row_in <= row_req;
	    col_in <= col_req;
	    row1 <= {8'h1,8'h1,8'h1,8'h1,8'h1,8'h1,8'h1,8'h1,8'h1,8'h1,8'h1,8'h1,8'h1,8'h1,8'h1,8'h1,8'h1,8'h1,8'h1,8'h1,8'h1,8'h1,8'h1,8'h1,8'h1,8'h1,8'h1,8'h1,8'h1,8'h1,8'h1,8'h1};
	    col2 <= {8'h1,8'h1,8'h1,8'h1,8'h1,8'h1,8'h1,8'h1,8'h1,8'h1,8'h1,8'h1,8'h1,8'h1,8'h1,8'h1,8'h1,8'h1,8'h1,8'h1,8'h1,8'h1,8'h1,8'h1,8'h1,8'h1,8'h1,8'h1,8'h1,8'h1,8'h1,8'h1};
	    val_rows <= 1;
	    #20;
	    val_rows <= 0;
	  end
	  #20;  
	end
	val_rows = 0;
        #200
	
	$display("Finishing Sim"); //print nice message
        $finish;
  end

endmodule  	   

`default_nettype wire

iter_dummy.vcd
$date
	Wed Dec 14 00:34:22 2022
$end
$version
	Icarus Verilog
$end
$timescale
	1ps
$end
$scope module tb_iter_control $end
$var wire 1 ! val_out $end
$var wire 5 " row_req [4:0] $end
$var wire 5 # row_out [4:0] $end
$var wire 1 $ new_request $end
$var wire 8 % mat_out [7:0] $end
$var wire 1 & done $end
$var wire 5 ' col_req [4:0] $end
$var wire 5 ( col_out [4:0] $end
$var reg 1 ) clk $end
$var reg 256 * col2 [255:0] $end
$var reg 5 + col_in [4:0] $end
$var reg 1 , complete $end
$var reg 256 - row1 [255:0] $end
$var reg 5 . row_in [4:0] $end
$var reg 1 / rst $end
$var reg 1 0 val_rows $end
$scope module test_alg $end
$var wire 1 ) clk_in $end
$var wire 5 1 col_in [4:0] $end
$var wire 1 , complete $end
$var wire 256 2 matA_row [255:0] $end
$var wire 256 3 matB_col [255:0] $end
$var wire 5 4 row_in [4:0] $end
$var wire 1 / rst_in $end
$var wire 1 0 val_rows $end
$var reg 5 5 col_out [4:0] $end
$var reg 5 6 col_req [4:0] $end
$var reg 1 7 complete_old $end
$var reg 2 8 control_state [1:0] $end
$var reg 1 & done $end
$var reg 8 9 matrix_val [7:0] $end
$var reg 1 $ new_request $end
$var reg 5 : row_out [4:0] $end
$var reg 5 ; row_req [4:0] $end
$var reg 1 ! valid_out $end
$upscope $end
$upscope $end
$enddefinitions $end
#0
$dumpvars
bx ;
bx :
bx 9
bx 8
x7
bx 6
bx 5
bx 4
bx 3
bx 2
bx 1
x0
0/
bx .
bx -
0,
bx +
bx *
0)
bx (
bx '
x&
bx %
x$
bx #
bx "
x!
$end
#10000
07
1)
#20000
0)
#30000
b0 8
0!
b0 %
b0 9
0&
b0 '
b0 6
b0 "
b0 ;
b0 (
b0 5
b0 #
b0 :
1)
1/
#40000
0)
#50000
1)
0/
#60000
0)
#70000
1$
b1 8
17
1)
1,
#80000
0)
#90000
07
1)
0,
#100000
0)
#110000
1)
#120000
0)
#130000
1)
#140000
0)
#150000
10
b100000001000000010000000100000001000000010000000100000001000000010000000100000001000000010000000100000001000000010000000100000001000000010000000100000001000000010000000100000001000000010000000100000001000000010000000100000001000000010000000100000001 *
b100000001000000010000000100000001000000010000000100000001000000010000000100000001000000010000000100000001000000010000000100000001000000010000000100000001000000010000000100000001000000010000000100000001000000010000000100000001000000010000000100000001 3
b100000001000000010000000100000001000000010000000100000001000000010000000100000001000000010000000100000001000000010000000100000001000000010000000100000001000000010000000100000001000000010000000100000001000000010000000100000001000000010000000100000001 -
b100000001000000010000000100000001000000010000000100000001000000010000000100000001000000010000000100000001000000010000000100000001000000010000000100000001000000010000000100000001000000010000000100000001000000010000000100000001000000010000000100000001 2
b0 +
b0 1
b0 .
b0 4
1)
#160000
0)
#170000
b1 '
b1 6
1!
b1 %
b1 9
00
1)
#180000
0)
#190000
10
b1 +
b1 1
1)
#200000
0)
#210000
b10 '
b10 6
b1 (
b1 5
00
1)
#220000
0)
#230000
10
b10 +
b10 1
1)
#240000
0)
#250000
b11 '
b11 6
b10 (
b10 5
00
1)
#260000
0)
#270000
10
b11 +
b11 1
1)
#280000
0)
#290000
b100 '
b100 6
b11 (
b11 5
00
1)
#300000
0)
#310000
10
b100 +
b100 1
1)
#320000
0)
#330000
b101 '
b101 6
b100 (
b100 5
00
1)
#340000
0)
#350000
10
b101 +
b101 1
1)
#360000
0)
#370000
b110 '
b110 6
b101 (
b101 5
00
1)
#380000
0)
#390000
10
b110 +
b110 1
1)
#400000
0)
#410000
b111 '
b111 6
b110 (
b110 5
00
1)
#420000
0)
#430000
10
b111 +
b111 1
1)
#440000
0)
#450000
b1000 '
b1000 6
b111 (
b111 5
00
1)
#460000
0)
#470000
10
b1000 +
b1000 1
1)
#480000
0)
#490000
b1001 '
b1001 6
b1000 (
b1000 5
00
1)
#500000
0)
#510000
10
b1001 +
b1001 1
1)
#520000
0)
#530000
b1010 '
b1010 6
b1001 (
b1001 5
00
1)
#540000
0)
#550000
10
b1010 +
b1010 1
1)
#560000
0)
#570000
b1011 '
b1011 6
b1010 (
b1010 5
00
1)
#580000
0)
#590000
10
b1011 +
b1011 1
1)
#600000
0)
#610000
b1100 '
b1100 6
b1011 (
b1011 5
00
1)
#620000
0)
#630000
10
b1100 +
b1100 1
1)
#640000
0)
#650000
b1101 '
b1101 6
b1100 (
b1100 5
00
1)
#660000
0)
#670000
10
b1101 +
b1101 1
1)
#680000
0)
#690000
b1110 '
b1110 6
b1101 (
b1101 5
00
1)
#700000
0)
#710000
10
b1110 +
b1110 1
1)
#720000
0)
#730000
b1111 '
b1111 6
b1110 (
b1110 5
00
1)
#740000
0)
#750000
10
b1111 +
b1111 1
1)
#760000
0)
#770000
b10000 '
b10000 6
b1111 (
b1111 5
00
1)
#780000
0)
#790000
10
b10000 +
b10000 1
1)
#800000
0)
#810000
b10001 '
b10001 6
b10000 (
b10000 5
00
1)
#820000
0)
#830000
10
b10001 +
b10001 1
1)
#840000
0)
#850000
b10010 '
b10010 6
b10001 (
b10001 5
00
1)
#860000
0)
#870000
10
b10010 +
b10010 1
1)
#880000
0)
#890000
b10011 '
b10011 6
b10010 (
b10010 5
00
1)
#900000
0)
#910000
10
b10011 +
b10011 1
1)
#920000
0)
#930000
b10100 '
b10100 6
b10011 (
b10011 5
00
1)
#940000
0)
#950000
10
b10100 +
b10100 1
1)
#960000
0)
#970000
b10101 '
b10101 6
b10100 (
b10100 5
00
1)
#980000
0)
#990000
10
b10101 +
b10101 1
1)
#1000000
0)
#1010000
b10110 '
b10110 6
b10101 (
b10101 5
00
1)
#1020000
0)
#1030000
10
b10110 +
b10110 1
1)
#1040000
0)
#1050000
b10111 '
b10111 6
b10110 (
b10110 5
00
1)
#1060000
0)
#1070000
10
b10111 +
b10111 1
1)
#1080000
0)
#1090000
b11000 '
b11000 6
b10111 (
b10111 5
00
1)
#1100000
0)
#1110000
10
b11000 +
b11000 1
1)
#1120000
0)
#1130000
b11001 '
b11001 6
b11000 (
b11000 5
00
1)
#1140000
0)
#1150000
10
b11001 +
b11001 1
1)
#1160000
0)
#1170000
b11010 '
b11010 6
b11001 (
b11001 5
00
1)
#1180000
0)
#1190000
10
b11010 +
b11010 1
1)
#1200000
0)
#1210000
b11011 '
b11011 6
b11010 (
b11010 5
00
1)
#1220000
0)
#1230000
10
b11011 +
b11011 1
1)
#1240000
0)
#1250000
b11100 '
b11100 6
b11011 (
b11011 5
00
1)
#1260000
0)
#1270000
10
b11100 +
b11100 1
1)
#1280000
0)
#1290000
b11101 '
b11101 6
b11100 (
b11100 5
00
1)
#1300000
0)
#1310000
10
b11101 +
b11101 1
1)
#1320000
0)
#1330000
b11110 '
b11110 6
b11101 (
b11101 5
00
1)
#1340000
0)
#1350000
10
b11110 +
b11110 1
1)
#1360000
0)
#1370000
b11111 '
b11111 6
b11110 (
b11110 5
00
1)
#1380000
0)
#1390000
10
b11111 +
b11111 1
1)
#1400000
0)
#1410000
b0 '
b0 6
b1 "
b1 ;
b11111 (
b11111 5
00
1)
#1420000
0)
#1430000
10
b0 +
b0 1
b1 .
b1 4
1)
#1440000
0)
#1450000
b1 '
b1 6
b0 (
b0 5
b1 #
b1 :
00
1)
#1460000
0)
#1470000
10
b1 +
b1 1
1)
#1480000
0)
#1490000
b10 '
b10 6
b1 (
b1 5
00
1)
#1500000
0)
#1510000
10
b10 +
b10 1
1)
#1520000
0)
#1530000
b11 '
b11 6
b10 (
b10 5
00
1)
#1540000
0)
#1550000
10
b11 +
b11 1
1)
#1560000
0)
#1570000
b100 '
b100 6
b11 (
b11 5
00
1)
#1580000
0)
#1590000
10
b100 +
b100 1
1)
#1600000
0)
#1610000
b101 '
b101 6
b100 (
b100 5
00
1)
#1620000
0)
#1630000
10
b101 +
b101 1
1)
#1640000
0)
#1650000
b110 '
b110 6
b101 (
b101 5
00
1)
#1660000
0)
#1670000
10
b110 +
b110 1
1)
#1680000
0)
#1690000
b111 '
b111 6
b110 (
b110 5
00
1)
#1700000
0)
#1710000
10
b111 +
b111 1
1)
#1720000
0)
#1730000
b1000 '
b1000 6
b111 (
b111 5
00
1)
#1740000
0)
#1750000
10
b1000 +
b1000 1
1)
#1760000
0)
#1770000
b1001 '
b1001 6
b1000 (
b1000 5
00
1)
#1780000
0)
#1790000
10
b1001 +
b1001 1
1)
#1800000
0)
#1810000
b1010 '
b1010 6
b1001 (
b1001 5
00
1)
#1820000
0)
#1830000
10
b1010 +
b1010 1
1)
#1840000
0)
#1850000
b1011 '
b1011 6
b1010 (
b1010 5
00
1)
#1860000
0)
#1870000
10
b1011 +
b1011 1
1)
#1880000
0)
#1890000
b1100 '
b1100 6
b1011 (
b1011 5
00
1)
#1900000
0)
#1910000
10
b1100 +
b1100 1
1)
#1920000
0)
#1930000
b1101 '
b1101 6
b1100 (
b1100 5
00
1)
#1940000
0)
#1950000
10
b1101 +
b1101 1
1)
#1960000
0)
#1970000
b1110 '
b1110 6
b1101 (
b1101 5
00
1)
#1980000
0)
#1990000
10
b1110 +
b1110 1
1)
#2000000
0)
#2010000
b1111 '
b1111 6
b1110 (
b1110 5
00
1)
#2020000
0)
#2030000
10
b1111 +
b1111 1
1)
#2040000
0)
#2050000
b10000 '
b10000 6
b1111 (
b1111 5
00
1)
#2060000
0)
#2070000
10
b10000 +
b10000 1
1)
#2080000
0)
#2090000
b10001 '
b10001 6
b10000 (
b10000 5
00
1)
#2100000
0)
#2110000
10
b10001 +
b10001 1
1)
#2120000
0)
#2130000
b10010 '
b10010 6
b10001 (
b10001 5
00
1)
#2140000
0)
#2150000
10
b10010 +
b10010 1
1)
#2160000
0)
#2170000
b10011 '
b10011 6
b10010 (
b10010 5
00
1)
#2180000
0)
#2190000
10
b10011 +
b10011 1
1)
#2200000
0)
#2210000
b10100 '
b10100 6
b10011 (
b10011 5
00
1)
#2220000
0)
#2230000
10
b10100 +
b10100 1
1)
#2240000
0)
#2250000
b10101 '
b10101 6
b10100 (
b10100 5
00
1)
#2260000
0)
#2270000
10
b10101 +
b10101 1
1)
#2280000
0)
#2290000
b10110 '
b10110 6
b10101 (
b10101 5
00
1)
#2300000
0)
#2310000
10
b10110 +
b10110 1
1)
#2320000
0)
#2330000
b10111 '
b10111 6
b10110 (
b10110 5
00
1)
#2340000
0)
#2350000
10
b10111 +
b10111 1
1)
#2360000
0)
#2370000
b11000 '
b11000 6
b10111 (
b10111 5
00
1)
#2380000
0)
#2390000
10
b11000 +
b11000 1
1)
#2400000
0)
#2410000
b11001 '
b11001 6
b11000 (
b11000 5
00
1)
#2420000
0)
#2430000
10
b11001 +
b11001 1
1)
#2440000
0)
#2450000
b11010 '
b11010 6
b11001 (
b11001 5
00
1)
#2460000
0)
#2470000
10
b11010 +
b11010 1
1)
#2480000
0)
#2490000
b11011 '
b11011 6
b11010 (
b11010 5
00
1)
#2500000
0)
#2510000
10
b11011 +
b11011 1
1)
#2520000
0)
#2530000
b11100 '
b11100 6
b11011 (
b11011 5
00
1)
#2540000
0)
#2550000
10
b11100 +
b11100 1
1)
#2560000
0)
#2570000
b11101 '
b11101 6
b11100 (
b11100 5
00
1)
#2580000
0)
#2590000
10
b11101 +
b11101 1
1)
#2600000
0)
#2610000
b11110 '
b11110 6
b11101 (
b11101 5
00
1)
#2620000
0)
#2630000
10
b11110 +
b11110 1
1)
#2640000
0)
#2650000
b11111 '
b11111 6
b11110 (
b11110 5
00
1)
#2660000
0)
#2670000
10
b11111 +
b11111 1
1)
#2680000
0)
#2690000
b0 '
b0 6
b10 "
b10 ;
b11111 (
b11111 5
00
1)
#2700000
0)
#2710000
10
b0 +
b0 1
b10 .
b10 4
1)
#2720000
0)
#2730000
b1 '
b1 6
b0 (
b0 5
b10 #
b10 :
00
1)
#2740000
0)
#2750000
10
b1 +
b1 1
1)
#2760000
0)
#2770000
b10 '
b10 6
b1 (
b1 5
00
1)
#2780000
0)
#2790000
10
b10 +
b10 1
1)
#2800000
0)
#2810000
b11 '
b11 6
b10 (
b10 5
00
1)
#2820000
0)
#2830000
10
b11 +
b11 1
1)
#2840000
0)
#2850000
b100 '
b100 6
b11 (
b11 5
00
1)
#2860000
0)
#2870000
10
b100 +
b100 1
1)
#2880000
0)
#2890000
b101 '
b101 6
b100 (
b100 5
00
1)
#2900000
0)
#2910000
10
b101 +
b101 1
1)
#2920000
0)
#2930000
b110 '
b110 6
b101 (
b101 5
00
1)
#2940000
0)
#2950000
10
b110 +
b110 1
1)
#2960000
0)
#2970000
b111 '
b111 6
b110 (
b110 5
00
1)
#2980000
0)
#2990000
10
b111 +
b111 1
1)
#3000000
0)
#3010000
b1000 '
b1000 6
b111 (
b111 5
00
1)
#3020000
0)
#3030000
10
b1000 +
b1000 1
1)
#3040000
0)
#3050000
b1001 '
b1001 6
b1000 (
b1000 5
00
1)
#3060000
0)
#3070000
10
b1001 +
b1001 1
1)
#3080000
0)
#3090000
b1010 '
b1010 6
b1001 (
b1001 5
00
1)
#3100000
0)
#3110000
10
b1010 +
b1010 1
1)
#3120000
0)
#3130000
b1011 '
b1011 6
b1010 (
b1010 5
00
1)
#3140000
0)
#3150000
10
b1011 +
b1011 1
1)
#3160000
0)
#3170000
b1100 '
b1100 6
b1011 (
b1011 5
00
1)
#3180000
0)
#3190000
10
b1100 +
b1100 1
1)
#3200000
0)
#3210000
b1101 '
b1101 6
b1100 (
b1100 5
00
1)
#3220000
0)
#3230000
10
b1101 +
b1101 1
1)
#3240000
0)
#3250000
b1110 '
b1110 6
b1101 (
b1101 5
00
1)
#3260000
0)
#3270000
10
b1110 +
b1110 1
1)
#3280000
0)
#3290000
b1111 '
b1111 6
b1110 (
b1110 5
00
1)
#3300000
0)
#3310000
10
b1111 +
b1111 1
1)
#3320000
0)
#3330000
b10000 '
b10000 6
b1111 (
b1111 5
00
1)
#3340000
0)
#3350000
10
b10000 +
b10000 1
1)
#3360000
0)
#3370000
b10001 '
b10001 6
b10000 (
b10000 5
00
1)
#3380000
0)
#3390000
10
b10001 +
b10001 1
1)
#3400000
0)
#3410000
b10010 '
b10010 6
b10001 (
b10001 5
00
1)
#3420000
0)
#3430000
10
b10010 +
b10010 1
1)
#3440000
0)
#3450000
b10011 '
b10011 6
b10010 (
b10010 5
00
1)
#3460000
0)
#3470000
10
b10011 +
b10011 1
1)
#3480000
0)
#3490000
b10100 '
b10100 6
b10011 (
b10011 5
00
1)
#3500000
0)
#3510000
10
b10100 +
b10100 1
1)
#3520000
0)
#3530000
b10101 '
b10101 6
b10100 (
b10100 5
00
1)
#3540000
0)
#3550000
10
b10101 +
b10101 1
1)
#3560000
0)
#3570000
b10110 '
b10110 6
b10101 (
b10101 5
00
1)
#3580000
0)
#3590000
10
b10110 +
b10110 1
1)
#3600000
0)
#3610000
b10111 '
b10111 6
b10110 (
b10110 5
00
1)
#3620000
0)
#3630000
10
b10111 +
b10111 1
1)
#3640000
0)
#3650000
b11000 '
b11000 6
b10111 (
b10111 5
00
1)
#3660000
0)
#3670000
10
b11000 +
b11000 1
1)
#3680000
0)
#3690000
b11001 '
b11001 6
b11000 (
b11000 5
00
1)
#3700000
0)
#3710000
10
b11001 +
b11001 1
1)
#3720000
0)
#3730000
b11010 '
b11010 6
b11001 (
b11001 5
00
1)
#3740000
0)
#3750000
10
b11010 +
b11010 1
1)
#3760000
0)
#3770000
b11011 '
b11011 6
b11010 (
b11010 5
00
1)
#3780000
0)
#3790000
10
b11011 +
b11011 1
1)
#3800000
0)
#3810000
b11100 '
b11100 6
b11011 (
b11011 5
00
1)
#3820000
0)
#3830000
10
b11100 +
b11100 1
1)
#3840000
0)
#3850000
b11101 '
b11101 6
b11100 (
b11100 5
00
1)
#3860000
0)
#3870000
10
b11101 +
b11101 1
1)
#3880000
0)
#3890000
b11110 '
b11110 6
b11101 (
b11101 5
00
1)
#3900000
0)
#3910000
10
b11110 +
b11110 1
1)
#3920000
0)
#3930000
b11111 '
b11111 6
b11110 (
b11110 5
00
1)
#3940000
0)
#3950000
10
b11111 +
b11111 1
1)
#3960000
0)
#3970000
b0 '
b0 6
b11 "
b11 ;
b11111 (
b11111 5
00
1)
#3980000
0)
#3990000
10
b0 +
b0 1
b11 .
b11 4
1)
#4000000
0)
#4010000
b1 '
b1 6
b0 (
b0 5
b11 #
b11 :
00
1)
#4020000
0)
#4030000
10
b1 +
b1 1
1)
#4040000
0)
#4050000
b10 '
b10 6
b1 (
b1 5
00
1)
#4060000
0)
#4070000
10
b10 +
b10 1
1)
#4080000
0)
#4090000
b11 '
b11 6
b10 (
b10 5
00
1)
#4100000
0)
#4110000
10
b11 +
b11 1
1)
#4120000
0)
#4130000
b100 '
b100 6
b11 (
b11 5
00
1)
#4140000
0)
#4150000
10
b100 +
b100 1
1)
#4160000
0)
#4170000
b101 '
b101 6
b100 (
b100 5
00
1)
#4180000
0)
#4190000
10
b101 +
b101 1
1)
#4200000
0)
#4210000
b110 '
b110 6
b101 (
b101 5
00
1)
#4220000
0)
#4230000
10
b110 +
b110 1
1)
#4240000
0)
#4250000
b111 '
b111 6
b110 (
b110 5
00
1)
#4260000
0)
#4270000
10
b111 +
b111 1
1)
#4280000
0)
#4290000
b1000 '
b1000 6
b111 (
b111 5
00
1)
#4300000
0)
#4310000
10
b1000 +
b1000 1
1)
#4320000
0)
#4330000
b1001 '
b1001 6
b1000 (
b1000 5
00
1)
#4340000
0)
#4350000
10
b1001 +
b1001 1
1)
#4360000
0)
#4370000
b1010 '
b1010 6
b1001 (
b1001 5
00
1)
#4380000
0)
#4390000
10
b1010 +
b1010 1
1)
#4400000
0)
#4410000
b1011 '
b1011 6
b1010 (
b1010 5
00
1)
#4420000
0)
#4430000
10
b1011 +
b1011 1
1)
#4440000
0)
#4450000
b1100 '
b1100 6
b1011 (
b1011 5
00
1)
#4460000
0)
#4470000
10
b1100 +
b1100 1
1)
#4480000
0)
#4490000
b1101 '
b1101 6
b1100 (
b1100 5
00
1)
#4500000
0)
#4510000
10
b1101 +
b1101 1
1)
#4520000
0)
#4530000
b1110 '
b1110 6
b1101 (
b1101 5
00
1)
#4540000
0)
#4550000
10
b1110 +
b1110 1
1)
#4560000
0)
#4570000
b1111 '
b1111 6
b1110 (
b1110 5
00
1)
#4580000
0)
#4590000
10
b1111 +
b1111 1
1)
#4600000
0)
#4610000
b10000 '
b10000 6
b1111 (
b1111 5
00
1)
#4620000
0)
#4630000
10
b10000 +
b10000 1
1)
#4640000
0)
#4650000
b10001 '
b10001 6
b10000 (
b10000 5
00
1)
#4660000
0)
#4670000
10
b10001 +
b10001 1
1)
#4680000
0)
#4690000
b10010 '
b10010 6
b10001 (
b10001 5
00
1)
#4700000
0)
#4710000
10
b10010 +
b10010 1
1)
#4720000
0)
#4730000
b10011 '
b10011 6
b10010 (
b10010 5
00
1)
#4740000
0)
#4750000
10
b10011 +
b10011 1
1)
#4760000
0)
#4770000
b10100 '
b10100 6
b10011 (
b10011 5
00
1)
#4780000
0)
#4790000
10
b10100 +
b10100 1
1)
#4800000
0)
#4810000
b10101 '
b10101 6
b10100 (
b10100 5
00
1)
#4820000
0)
#4830000
10
b10101 +
b10101 1
1)
#4840000
0)
#4850000
b10110 '
b10110 6
b10101 (
b10101 5
00
1)
#4860000
0)
#4870000
10
b10110 +
b10110 1
1)
#4880000
0)
#4890000
b10111 '
b10111 6
b10110 (
b10110 5
00
1)
#4900000
0)
#4910000
10
b10111 +
b10111 1
1)
#4920000
0)
#4930000
b11000 '
b11000 6
b10111 (
b10111 5
00
1)
#4940000
0)
#4950000
10
b11000 +
b11000 1
1)
#4960000
0)
#4970000
b11001 '
b11001 6
b11000 (
b11000 5
00
1)
#4980000
0)
#4990000
10
b11001 +
b11001 1
1)
#5000000
0)
#5010000
b11010 '
b11010 6
b11001 (
b11001 5
00
1)
#5020000
0)
#5030000
10
b11010 +
b11010 1
1)
#5040000
0)
#5050000
b11011 '
b11011 6
b11010 (
b11010 5
00
1)
#5060000
0)
#5070000
10
b11011 +
b11011 1
1)
#5080000
0)
#5090000
b11100 '
b11100 6
b11011 (
b11011 5
00
1)
#5100000
0)
#5110000
10
b11100 +
b11100 1
1)
#5120000
0)
#5130000
b11101 '
b11101 6
b11100 (
b11100 5
00
1)
#5140000
0)
#5150000
10
b11101 +
b11101 1
1)
#5160000
0)
#5170000
b11110 '
b11110 6
b11101 (
b11101 5
00
1)
#5180000
0)
#5190000
10
b11110 +
b11110 1
1)
#5200000
0)
#5210000
b11111 '
b11111 6
b11110 (
b11110 5
00
1)
#5220000
0)
#5230000
10
b11111 +
b11111 1
1)
#5240000
0)
#5250000
b0 '
b0 6
b100 "
b100 ;
b11111 (
b11111 5
00
1)
#5260000
0)
#5270000
10
b0 +
b0 1
b100 .
b100 4
1)
#5280000
0)
#5290000
b1 '
b1 6
b0 (
b0 5
b100 #
b100 :
00
1)
#5300000
0)
#5310000
10
b1 +
b1 1
1)
#5320000
0)
#5330000
b10 '
b10 6
b1 (
b1 5
00
1)
#5340000
0)
#5350000
10
b10 +
b10 1
1)
#5360000
0)
#5370000
b11 '
b11 6
b10 (
b10 5
00
1)
#5380000
0)
#5390000
10
b11 +
b11 1
1)
#5400000
0)
#5410000
b100 '
b100 6
b11 (
b11 5
00
1)
#5420000
0)
#5430000
10
b100 +
b100 1
1)
#5440000
0)
#5450000
b101 '
b101 6
b100 (
b100 5
00
1)
#5460000
0)
#5470000
10
b101 +
b101 1
1)
#5480000
0)
#5490000
b110 '
b110 6
b101 (
b101 5
00
1)
#5500000
0)
#5510000
10
b110 +
b110 1
1)
#5520000
0)
#5530000
b111 '
b111 6
b110 (
b110 5
00
1)
#5540000
0)
#5550000
10
b111 +
b111 1
1)
#5560000
0)
#5570000
b1000 '
b1000 6
b111 (
b111 5
00
1)
#5580000
0)
#5590000
10
b1000 +
b1000 1
1)
#5600000
0)
#5610000
b1001 '
b1001 6
b1000 (
b1000 5
00
1)
#5620000
0)
#5630000
10
b1001 +
b1001 1
1)
#5640000
0)
#5650000
b1010 '
b1010 6
b1001 (
b1001 5
00
1)
#5660000
0)
#5670000
10
b1010 +
b1010 1
1)
#5680000
0)
#5690000
b1011 '
b1011 6
b1010 (
b1010 5
00
1)
#5700000
0)
#5710000
10
b1011 +
b1011 1
1)
#5720000
0)
#5730000
b1100 '
b1100 6
b1011 (
b1011 5
00
1)
#5740000
0)
#5750000
10
b1100 +
b1100 1
1)
#5760000
0)
#5770000
b1101 '
b1101 6
b1100 (
b1100 5
00
1)
#5780000
0)
#5790000
10
b1101 +
b1101 1
1)
#5800000
0)
#5810000
b1110 '
b1110 6
b1101 (
b1101 5
00
1)
#5820000
0)
#5830000
10
b1110 +
b1110 1
1)
#5840000
0)
#5850000
b1111 '
b1111 6
b1110 (
b1110 5
00
1)
#5860000
0)
#5870000
10
b1111 +
b1111 1
1)
#5880000
0)
#5890000
b10000 '
b10000 6
b1111 (
b1111 5
00
1)
#5900000
0)
#5910000
10
b10000 +
b10000 1
1)
#5920000
0)
#5930000
b10001 '
b10001 6
b10000 (
b10000 5
00
1)
#5940000
0)
#5950000
10
b10001 +
b10001 1
1)
#5960000
0)
#5970000
b10010 '
b10010 6
b10001 (
b10001 5
00
1)
#5980000
0)
#5990000
10
b10010 +
b10010 1
1)
#6000000
0)
#6010000
b10011 '
b10011 6
b10010 (
b10010 5
00
1)
#6020000
0)
#6030000
10
b10011 +
b10011 1
1)
#6040000
0)
#6050000
b10100 '
b10100 6
b10011 (
b10011 5
00
1)
#6060000
0)
#6070000
10
b10100 +
b10100 1
1)
#6080000
0)
#6090000
b10101 '
b10101 6
b10100 (
b10100 5
00
1)
#6100000
0)
#6110000
10
b10101 +
b10101 1
1)
#6120000
0)
#6130000
b10110 '
b10110 6
b10101 (
b10101 5
00
1)
#6140000
0)
#6150000
10
b10110 +
b10110 1
1)
#6160000
0)
#6170000
b10111 '
b10111 6
b10110 (
b10110 5
00
1)
#6180000
0)
#6190000
10
b10111 +
b10111 1
1)
#6200000
0)
#6210000
b11000 '
b11000 6
b10111 (
b10111 5
00
1)
#6220000
0)
#6230000
10
b11000 +
b11000 1
1)
#6240000
0)
#6250000
b11001 '
b11001 6
b11000 (
b11000 5
00
1)
#6260000
0)
#6270000
10
b11001 +
b11001 1
1)
#6280000
0)
#6290000
b11010 '
b11010 6
b11001 (
b11001 5
00
1)
#6300000
0)
#6310000
10
b11010 +
b11010 1
1)
#6320000
0)
#6330000
b11011 '
b11011 6
b11010 (
b11010 5
00
1)
#6340000
0)
#6350000
10
b11011 +
b11011 1
1)
#6360000
0)
#6370000
b11100 '
b11100 6
b11011 (
b11011 5
00
1)
#6380000
0)
#6390000
10
b11100 +
b11100 1
1)
#6400000
0)
#6410000
b11101 '
b11101 6
b11100 (
b11100 5
00
1)
#6420000
0)
#6430000
10
b11101 +
b11101 1
1)
#6440000
0)
#6450000
b11110 '
b11110 6
b11101 (
b11101 5
00
1)
#6460000
0)
#6470000
10
b11110 +
b11110 1
1)
#6480000
0)
#6490000
b11111 '
b11111 6
b11110 (
b11110 5
00
1)
#6500000
0)
#6510000
10
b11111 +
b11111 1
1)
#6520000
0)
#6530000
b0 '
b0 6
b101 "
b101 ;
b11111 (
b11111 5
00
1)
#6540000
0)
#6550000
10
b0 +
b0 1
b101 .
b101 4
1)
#6560000
0)
